resurrector/__init__.py
resurrector/backup_resolver.py
resurrector/db_handler.py
resurrector-0.0.7.dist-info/METADATA
resurrector-0.0.7.dist-info/WHEEL
resurrector-0.0.7.dist-info/top_level.txt
resurrector-0.0.7.dist-info/RECORD
