Metadata-Version: 2.1
Name: resurrector
Version: 0.0.7
Summary: Restoring MySQL Databases from their backups
Home-page: UNKNOWN
Author: rexshijaku (Rexhep Shijaku)
Author-email: <rexhepshijaku@gmail.com>
License: UNKNOWN
Keywords: python,mysql,database,backup,restore
Platform: UNKNOWN
Classifier: Development Status :: 1 - Planning
Classifier: Intended Audience :: Developers
Classifier: Programming Language :: Python :: 3
Classifier: Operating System :: Unix
Classifier: Operating System :: MacOS :: MacOS X
Classifier: Operating System :: Microsoft :: Windows
